crawlab/__init__.py
crawlab/_version.py
crawlab/context_manager.py
crawlab/crawler.py
crawlab/magic_crawler.py
crawlab/proxy.py
crawlab/settings.py
crawlab/utils.py
crawlab/widgets.py
crawlab/static/extension.js
crawlab/static/index.js
crawlab/static/index.js.map
crawlab-0.1.0a6.data/data/etc/jupyter/nbconfig/notebook.d/crawlab.json
crawlab-0.1.0a6.data/data/share/jupyter/nbextensions/crawlab/extension.js
crawlab-0.1.0a6.data/data/share/jupyter/nbextensions/crawlab/index.js
crawlab-0.1.0a6.data/data/share/jupyter/nbextensions/crawlab/index.js.map
crawlab-0.1.0a6.dist-info/METADATA
crawlab-0.1.0a6.dist-info/RECORD
crawlab-0.1.0a6.dist-info/WHEEL
crawlab-0.1.0a6.dist-info/top_level.txt
